core_commons/__init__.py
core_commons/exceptions/__init__.py
core_commons/exceptions/base_error.py
core_commons/exceptions/core_errors.py
core_commons/handlers/__init__.py
core_commons/handlers/codification_handler.py
core_commons/handlers/command_handler.py
core_commons/handlers/configuration_handler.py
core_commons/handlers/file_handler.py
core_commons/handlers/lockfile_handler.py
core_commons/handlers/net_handler.py
core_commons/models/__init__.py
core_commons/models/action_response.py
core_commons/scripting/__init__.py
core_commons/scripting/action_commons.py
core_commons/services/__init__.py
core_commons/services/git_client.py
core_commons/services/inventory.py
core_commons/types/__init__.py
core_commons/types/error_entity.py
core_commons-1.0.3.post3.dist-info/LICENSE.md
core_commons-1.0.3.post3.dist-info/METADATA
core_commons-1.0.3.post3.dist-info/WHEEL
core_commons-1.0.3.post3.dist-info/top_level.txt
core_commons-1.0.3.post3.dist-info/RECORD
