Metadata-Version: 2.1
Name: core-commons
Version: 1.0.3.post3
Summary: Implements common methods to use in most libraries and scripts for any environment.
Home-page: UNKNOWN
Author: The_Crazy_Sys_Admin
License: UNKNOWN
Platform: UNKNOWN
Requires-Python: >=3.6.8, <4
Requires-Dist: PyYaml
